[
    {
        "id": "1",
        "name": "Fanta",
        "prix": 1000,
        "description" : "La Fanta est tellement sucre mais j'aime la couleur Orange"
    },
    {
        "id": "2",
        "name": "Sprite",
        "prix": 1500,
        "description" : "Le Sprite ce jus gazeux qui est si petillant"
    },
    {
        "id": "3",
        "name": "A&W",
        "prix": 800,
        "description" : "A&W une boisson que je n'ai jamais essayer"
    },
    {
        "id": "4",
        "name": "Mtn-Dew",
        "prix": 1200,
        "description" : "Le Moutain Dew les pubs de cette boisson innondent la toile, est tellement mauvaise je deteste le gout"
    },
    {
        "id": "5",
        "name": "Orangina",
        "prix": 1000,
        "description" : "L'Orangina est tellement sucre mais j'aime la couleur Orange"
    },
    {
        "id": "6",
        "name": "Pepsi",
        "prix": 1500,
        "description" : "Le Pepsi boisson concurrente du c*ca shutt, dites rien a Messi une alternative de choix pour son rival americain"
    },
    {
        "id": "7",
        "name": "Coca-Cola",
        "prix": 1000,
        "description" : "Le Coca-cola est une boisson emblematique americaine qui fait la joie des fast-food depuis belle lurette"
    }
]